[{"name": "clash", "path": "keyboards/atreus/keymaps/clash"}, {"name": "classic", "path": "keyboards/atreus/keymaps/classic"}, {"name": "default", "path": "keyboards/atreus/keymaps/default"}, {"name": "dvorak_42_key", "path": "keyboards/atreus/keymaps/dvorak_42_key"}, {"name": "erlandsona", "path": "keyboards/atreus/keymaps/erlandsona"}, {"name": "gerb", "path": "keyboards/atreus/keymaps/gerb"}, {"name": "henxing", "path": "keyboards/atreus/keymaps/henxing", "error": "Unknown"}, {"name": "ibnuda", "path": "keyboards/atreus/keymaps/ibnuda", "error": "Unknown"}, {"name": "jeremy", "path": "keyboards/atreus/keymaps/jeremy", "error": "Unknown"}, {"name": "kejadlen", "path": "keyboards/atreus/keymaps/kejadlen"}, {"name": "khitsule", "path": "keyboards/atreus/keymaps/khitsule"}, {"name": "manna-harbour_miryoku", "path": "keyboards/atreus/keymaps/manna-harbour_miryoku", "no-cpp": true, "error": "Unknown Error"}, {"name": "nojjan", "path": "keyboards/atreus/keymaps/nojjan"}, {"name": "ptillemans", "path": "keyboards/atreus/keymaps/ptillemans"}, {"name": "quartz64", "path": "keyboards/atreus/keymaps/quartz64"}, {"name": "replicaJunction", "path": "keyboards/atreus/keymaps/replicaJunction", "error": "Unknown"}, {"name": "ridingqwerty", "path": "keyboards/atreus/keymaps/ridingqwerty", "error": "Unknown"}, {"name": "talljoe", "path": "keyboards/atreus/keymaps/talljoe", "no-cpp": true, "error": "Unknown Error"}, {"name": "via", "path": "keyboards/atreus/keymaps/via"}, {"name": "workman", "path": "keyboards/atreus/keymaps/workman"}, {"name": "xk", "path": "keyboards/atreus/keymaps/xk"}, {"name": "xyverz", "path": "keyboards/atreus/keymaps/xyverz"}, {"name": "yttyx", "path": "keyboards/atreus/keymaps/yttyx"}]